setup.py
thonnyapp.egg-info/PKG-INFO
thonnyapp.egg-info/SOURCES.txt
thonnyapp.egg-info/dependency_links.txt
thonnyapp.egg-info/requires.txt
thonnyapp.egg-info/top_level.txt
thonnyappinstaller/__init__.py
thonnyappinstaller/shortcut.exe